kubesealpy/__init__.py
kubesealpy/certificate.py
kubesealpy/cli/__init__.py
kubesealpy/cli/main.py
kubesealpy/constants.py
kubesealpy/crypto.py
kubesealpy/exceptions.py
kubesealpy/models.py
kubesealpy/scopes.py
kubesealpy/sealer.py
kubesealpy/unsealer.py
kubesealpy-1.0.1.dist-info/METADATA
kubesealpy-1.0.1.dist-info/WHEEL
kubesealpy-1.0.1.dist-info/entry_points.txt
kubesealpy-1.0.1.dist-info/licenses/LICENSE
kubesealpy-1.0.1.dist-info/RECORD
