Metadata-Version: 2.4
Name: kubesealpy
Version: 1.0.1
Summary: Python library for sealing and unsealing Kubernetes Sealed Secrets
License: MIT
License-File: LICENSE
Requires-Python: >=3.9,<4.0
Classifier: Development Status :: 3 - Alpha
Classifier: Intended Audience :: Developers
Classifier: License :: OSI Approved :: MIT License
Classifier: Programming Language :: Python :: 3
Classifier: Programming Language :: Python :: 3.9
Classifier: Programming Language :: Python :: 3.10
Classifier: Programming Language :: Python :: 3.11
Classifier: Programming Language :: Python :: 3.12
Classifier: Programming Language :: Python :: 3.13
Classifier: Programming Language :: Python :: 3.14
Classifier: Topic :: Security :: Cryptography
Classifier: Topic :: System :: Systems Administration
Requires-Dist: cryptography (>=41.0.0)
Requires-Dist: eval-type-backport (>=0.2.0) ; python_version < "3.10"
Requires-Dist: httpx (>=0.25.0)
Requires-Dist: kubernetes (>=28.0.0)
Requires-Dist: pydantic (>=2.0.0)
Requires-Dist: pyyaml (>=6.0)
Project-URL: Homepage, https://gitlab.com/nighthawk-oss/kubesealpy
Project-URL: Issues, https://gitlab.com/nighthawk-oss/kubesealpy/-/issues
Project-URL: Repository, https://gitlab.com/nighthawk-oss/kubesealpy
